Sumador1b/sumador.v
module sumador (
    input  wire a,
    input  wire b,
    input  wire cin,
    output wire suma,
    output wire cout
);

    assign suma = a ^ b ^ cin;
    assign cout = (a & b) | (cin & (a ^ b));

endmodule

Sumador1b/sumador_tb.v
`timescale 1ns / 1ps

module sumador_tb;

    // Registros para controlar las entradas de prueba
    reg a;
    reg b;
    reg cin;

    // Cables para leer las salidas del módulo
    wire suma;
    wire cout;

    // Instancia del sumador (UUT: Unit Under Test)
    sumador uut (
        .a(a),
        .b(b),
        .cin(cin),
        .suma(suma),
        .cout(cout)
    );

    initial begin
        // Crear archivo de ondas para GTKWave
        $dumpfile("sumador.vcd");
        $dumpvars(0, sumador_tb);

        // Probar las 8 combinaciones posibles con retardos de 10ns (#10)
        a = 0; b = 0; cin = 0; #10;
        a = 0; b = 0; cin = 1; #10;
        a = 0; b = 1; cin = 0; #10;
        a = 0; b = 1; cin = 1; #10;
        a = 1; b = 0; cin = 0; #10;
        a = 1; b = 0; cin = 1; #10;
        a = 1; b = 1; cin = 0; #10;
        a = 1; b = 1; cin = 1; #10;

        $finish;
    end

endmodule

Sumador1b/sumador.vcd
$date
	Sun Sep 27 20:30:25 2026
$end
$version
	Icarus Verilog
$end
$timescale
	1ps
$end
$scope module sumador_tb $end
$var wire 1 ! suma $end
$var wire 1 " cout $end
$var reg 1 # a $end
$var reg 1 $ b $end
$var reg 1 % cin $end
$scope module uut $end
$var wire 1 # a $end
$var wire 1 $ b $end
$var wire 1 % cin $end
$var wire 1 " cout $end
$var wire 1 ! suma $end
$upscope $end
$upscope $end
$enddefinitions $end
$comment Show the parameter values. $end
$dumpall
$end
#0
$dumpvars
0%
0$
0#
0"
0!
$end
#10000
1!
1%
#20000
0%
1$
#30000
1"
0!
1%
#40000
0"
1!
0%
0$
1#
#50000
1"
0!
1%
#60000
0%
1$
#70000
1!
1%
